build/test.txt
gui/__init__.py
gui/gui_5_0.py
model/__init__.py
model/lem_dnn1.4.py
prediction/__init__.py
prediction/prediction.py
preprocessing/__init__.py
preprocessing/preprocessing.py
loaneligibilitypredictionsystem-0.0.6.dist-info/METADATA
loaneligibilitypredictionsystem-0.0.6.dist-info/WHEEL
loaneligibilitypredictionsystem-0.0.6.dist-info/top_level.txt
loaneligibilitypredictionsystem-0.0.6.dist-info/RECORD
